epot_test/__init__.py
epot_test/main_test.py
epot_test-3.1.1.dist-info/WHEEL
epot_test-3.1.1.dist-info/METADATA
epot_test-3.1.1.dist-info/RECORD
